LICENSE
README.md
setup.py
confik/__init__.py
confik/exceptions.py
confik/parsers.py
confik/proxies.py
confik/utils.py
confik.egg-info/PKG-INFO
confik.egg-info/SOURCES.txt
confik.egg-info/dependency_links.txt
confik.egg-info/top_level.txt
tests/test_confik_parser.py
tests/test_read_environment_variables.py
tests/test_utils.py