Metadata-Version: 2.1
Name: confik
Version: 1.0.8
Summary: Config parser for environment variables
Home-page: https://github.com/LeOndaz/confik
Author: LeOndaz
Author-email: ahmeddark369@gmail.com
License-File: LICENSE
